dice/__init__.py
dice/__main__.py
dice/dice.py
puntdice-1.1.1.dist-info/LICENSE
puntdice-1.1.1.dist-info/METADATA
puntdice-1.1.1.dist-info/WHEEL
puntdice-1.1.1.dist-info/entry_points.txt
puntdice-1.1.1.dist-info/top_level.txt
puntdice-1.1.1.dist-info/RECORD
