Metadata-Version: 2.2
Name: puntdice
Version: 1.1.1
Summary: A Python dice roller command line utility and module.
Author-email: Themadpunter <themadpunter@proton.me>
Project-URL: Homepage, https://github.com/familycomicsstudios/dice
Classifier: Programming Language :: Python :: 3
Classifier: License :: OSI Approved :: MIT License
Classifier: Operating System :: OS Independent
Requires-Python: >=3.6
License-File: LICENSE
